comun_selenium.py
comun_selenium-0.3.dist-info/METADATA
comun_selenium-0.3.dist-info/WHEEL
comun_selenium-0.3.dist-info/top_level.txt
comun_selenium-0.3.dist-info/RECORD
