Metadata-Version: 2.1
Name: comun-selenium
Version: 0.3
Summary: UNKNOWN
Home-page: UNKNOWN
License: UNKNOWN
Platform: UNKNOWN
Requires-Dist: selenium
